moodlemlbackend/VERSION
moodlemlbackend/__init__.py
moodlemlbackend/chart.py
moodlemlbackend/evaluation.py
moodlemlbackend/export.py
moodlemlbackend/import.py
moodlemlbackend/prediction.py
moodlemlbackend/training.py
moodlemlbackend/version.py
moodlemlbackend/model/__init__.py
moodlemlbackend/model/tensor.py
moodlemlbackend/processor/__init__.py
moodlemlbackend/processor/estimator.py
moodlemlbackend/webapp/__init__.py
moodlemlbackend/webapp/access.py
moodlemlbackend/webapp/localfs.py
moodlemlbackend/webapp/s3.py
moodlemlbackend/webapp/util.py
moodlemlbackend-3.0.5.dist-info/LICENSE
moodlemlbackend-3.0.5.dist-info/METADATA
moodlemlbackend-3.0.5.dist-info/WHEEL
moodlemlbackend-3.0.5.dist-info/top_level.txt
moodlemlbackend-3.0.5.dist-info/RECORD
